tween/__init__.py
tween/__main__.py
tween/tween.py
tween-0.0.2.dist-info/LICENSE
tween-0.0.2.dist-info/METADATA
tween-0.0.2.dist-info/WHEEL
tween-0.0.2.dist-info/top_level.txt
tween-0.0.2.dist-info/RECORD
