Metadata-Version: 2.1
Name: tween
Version: 0.0.2
Summary: A small tweening module
Home-page: https://github.com/roodletoof/tween
Author: Ivar Fatland
Author-email: fatland99@hotmail.com
License: MIT
Platform: UNKNOWN
License-File: LICENSE
Requires-Dist: PyTweening (==1.0.3)
